<annotation verified="yes">
	<folder>object_detection</folder>
	<filename>15VWh2ypjeHFWKLN03KrTpyYXgrR71D91.jpg</filename>
	<path>/object_detection/15VWh2ypjeHFWKLN03KrTpyYXgrR71D91.jpg</path>
	<source>
		<database>Unknown</database>
	</source>
	<size>
		<width>640</width>
		<height>800</height>
		<depth>1</depth>
	</size>
	<segmented>0</segmented>
	<object>
		<name>tree</name>
		<pose>Unspecified</pose>
		<truncated>0</truncated>
		<difficult>0</difficult>
		<bndbox>
			<xmin>27</xmin>
			<ymin>26</ymin>
			<xmax>622</xmax>
			<ymax>750</ymax>
		</bndbox>
	</object>
	<object>
		<name>building</name>
		<pose>Unspecified</pose>
		<truncated>1</truncated>
		<difficult>0</difficult>
		<bndbox>
			<xmin>216</xmin>
			<ymin>475</ymin>
			<xmax>605</xmax>
			<ymax>800</ymax>
		</bndbox>
	</object>
	<object>
		<name>sky</name>
		<pose>Unspecified</pose>
		<truncated>1</truncated>
		<difficult>0</difficult>
		<bndbox>
			<xmin>20</xmin>
			<ymin>1</ymin>
			<xmax>640</xmax>
			<ymax>468</ymax>
		</bndbox>
	</object>
</annotation>
