<annotation verified="yes">
	<folder>object_detection</folder>
	<filename>19EVpZta_wV4jhWiqMuK2UFCBGLJ6BXnA.jpg</filename>
	<path>/object_detection/19EVpZta_wV4jhWiqMuK2UFCBGLJ6BXnA.jpg</path>
	<source>
		<database>Unknown</database>
	</source>
	<size>
		<width>454</width>
		<height>454</height>
		<depth>3</depth>
	</size>
	<segmented>0</segmented>
	<object>
		<name>building</name>
		<pose>Unspecified</pose>
		<truncated>1</truncated>
		<difficult>0</difficult>
		<bndbox>
			<xmin>302</xmin>
			<ymin>133</ymin>
			<xmax>454</xmax>
			<ymax>371</ymax>
		</bndbox>
	</object>
	<object>
		<name>building</name>
		<pose>Unspecified</pose>
		<truncated>1</truncated>
		<difficult>0</difficult>
		<bndbox>
			<xmin>335</xmin>
			<ymin>83</ymin>
			<xmax>454</xmax>
			<ymax>177</ymax>
		</bndbox>
	</object>
	<object>
		<name>building</name>
		<pose>Unspecified</pose>
		<truncated>0</truncated>
		<difficult>0</difficult>
		<bndbox>
			<xmin>80</xmin>
			<ymin>6</ymin>
			<xmax>209</xmax>
			<ymax>372</ymax>
		</bndbox>
	</object>
	<object>
		<name>building</name>
		<pose>Unspecified</pose>
		<truncated>0</truncated>
		<difficult>0</difficult>
		<bndbox>
			<xmin>201</xmin>
			<ymin>59</ymin>
			<xmax>269</xmax>
			<ymax>281</ymax>
		</bndbox>
	</object>
	<object>
		<name>building</name>
		<pose>Unspecified</pose>
		<truncated>0</truncated>
		<difficult>0</difficult>
		<bndbox>
			<xmin>193</xmin>
			<ymin>261</ymin>
			<xmax>304</xmax>
			<ymax>372</ymax>
		</bndbox>
	</object>
	<object>
		<name>building</name>
		<pose>Unspecified</pose>
		<truncated>1</truncated>
		<difficult>0</difficult>
		<bndbox>
			<xmin>1</xmin>
			<ymin>209</ymin>
			<xmax>142</xmax>
			<ymax>387</ymax>
		</bndbox>
	</object>
	<object>
		<name>light pole</name>
		<pose>Unspecified</pose>
		<truncated>1</truncated>
		<difficult>0</difficult>
		<bndbox>
			<xmin>73</xmin>
			<ymin>104</ymin>
			<xmax>152</xmax>
			<ymax>454</ymax>
		</bndbox>
	</object>
	<object>
		<name>car</name>
		<pose>Unspecified</pose>
		<truncated>0</truncated>
		<difficult>0</difficult>
		<bndbox>
			<xmin>360</xmin>
			<ymin>403</ymin>
			<xmax>447</xmax>
			<ymax>449</ymax>
		</bndbox>
	</object>
	<object>
		<name>car</name>
		<pose>Unspecified</pose>
		<truncated>1</truncated>
		<difficult>0</difficult>
		<bndbox>
			<xmin>150</xmin>
			<ymin>402</ymin>
			<xmax>210</xmax>
			<ymax>454</ymax>
		</bndbox>
	</object>
</annotation>
