<annotation verified="yes">
	<folder>object_detection</folder>
	<filename>1AQdv0Fb-xFicA-HSGGR5ABNRJaMedf-m.jpg</filename>
	<path>/object_detection/1AQdv0Fb-xFicA-HSGGR5ABNRJaMedf-m.jpg</path>
	<source>
		<database>Unknown</database>
	</source>
	<size>
		<width>640</width>
		<height>640</height>
		<depth>3</depth>
	</size>
	<segmented>0</segmented>
	<object>
		<name>tree</name>
		<pose>Unspecified</pose>
		<truncated>1</truncated>
		<difficult>0</difficult>
		<bndbox>
			<xmin>1</xmin>
			<ymin>1</ymin>
			<xmax>449</xmax>
			<ymax>445</ymax>
		</bndbox>
	</object>
	<object>
		<name>bridge</name>
		<pose>Unspecified</pose>
		<truncated>1</truncated>
		<difficult>0</difficult>
		<bndbox>
			<xmin>386</xmin>
			<ymin>40</ymin>
			<xmax>640</xmax>
			<ymax>349</ymax>
		</bndbox>
	</object>
</annotation>
