<annotation verified="yes">
	<folder>object_detection</folder>
	<filename>1AuagWe1yBi6dKfJe268tpPqzIG_sXJwZ.jpg</filename>
	<path>/object_detection/1AuagWe1yBi6dKfJe268tpPqzIG_sXJwZ.jpg</path>
	<source>
		<database>Unknown</database>
	</source>
	<size>
		<width>640</width>
		<height>640</height>
		<depth>3</depth>
	</size>
	<segmented>0</segmented>
	<object>
		<name>tent</name>
		<pose>Unspecified</pose>
		<truncated>0</truncated>
		<difficult>0</difficult>
		<bndbox>
			<xmin>369</xmin>
			<ymin>189</ymin>
			<xmax>531</xmax>
			<ymax>297</ymax>
		</bndbox>
	</object>
	<object>
		<name>tent</name>
		<pose>Unspecified</pose>
		<truncated>1</truncated>
		<difficult>0</difficult>
		<bndbox>
			<xmin>530</xmin>
			<ymin>172</ymin>
			<xmax>640</xmax>
			<ymax>300</ymax>
		</bndbox>
	</object>
	<object>
		<name>tree</name>
		<pose>Unspecified</pose>
		<truncated>0</truncated>
		<difficult>0</difficult>
		<bndbox>
			<xmin>187</xmin>
			<ymin>124</ymin>
			<xmax>299</xmax>
			<ymax>306</ymax>
		</bndbox>
	</object>
	<object>
		<name>sky</name>
		<pose>Unspecified</pose>
		<truncated>1</truncated>
		<difficult>0</difficult>
		<bndbox>
			<xmin>14</xmin>
			<ymin>1</ymin>
			<xmax>631</xmax>
			<ymax>186</ymax>
		</bndbox>
	</object>
	<object>
		<name>sun</name>
		<pose>Unspecified</pose>
		<truncated>0</truncated>
		<difficult>0</difficult>
		<bndbox>
			<xmin>125</xmin>
			<ymin>154</ymin>
			<xmax>200</xmax>
			<ymax>234</ymax>
		</bndbox>
	</object>
	<object>
		<name>sea</name>
		<pose>Unspecified</pose>
		<truncated>1</truncated>
		<difficult>0</difficult>
		<bndbox>
			<xmin>1</xmin>
			<ymin>242</ymin>
			<xmax>232</xmax>
			<ymax>287</ymax>
		</bndbox>
	</object>
	<object>
		<name>pool</name>
		<pose>Unspecified</pose>
		<truncated>1</truncated>
		<difficult>0</difficult>
		<bndbox>
			<xmin>376</xmin>
			<ymin>339</ymin>
			<xmax>640</xmax>
			<ymax>490</ymax>
		</bndbox>
	</object>
	<object>
		<name>pool</name>
		<pose>Unspecified</pose>
		<truncated>0</truncated>
		<difficult>0</difficult>
		<bndbox>
			<xmin>55</xmin>
			<ymin>284</ymin>
			<xmax>442</xmax>
			<ymax>385</ymax>
		</bndbox>
	</object>
	<object>
		<name>grass</name>
		<pose>Unspecified</pose>
		<truncated>1</truncated>
		<difficult>0</difficult>
		<bndbox>
			<xmin>308</xmin>
			<ymin>290</ymin>
			<xmax>640</xmax>
			<ymax>367</ymax>
		</bndbox>
	</object>
	<object>
		<name>chair</name>
		<pose>Unspecified</pose>
		<truncated>0</truncated>
		<difficult>0</difficult>
		<bndbox>
			<xmin>46</xmin>
			<ymin>373</ymin>
			<xmax>396</xmax>
			<ymax>568</ymax>
		</bndbox>
	</object>
	<object>
		<name>chair</name>
		<pose>Unspecified</pose>
		<truncated>1</truncated>
		<difficult>0</difficult>
		<bndbox>
			<xmin>1</xmin>
			<ymin>333</ymin>
			<xmax>276</xmax>
			<ymax>435</ymax>
		</bndbox>
	</object>
</annotation>
