<annotation verified="yes">
	<folder>object_detection</folder>
	<filename>1F6wPw3-nN4T3OvHk2A1bnWj7E7y7fRd8.jpg</filename>
	<path>/object_detection/1F6wPw3-nN4T3OvHk2A1bnWj7E7y7fRd8.jpg</path>
	<source>
		<database>Unknown</database>
	</source>
	<size>
		<width>600</width>
		<height>400</height>
		<depth>3</depth>
	</size>
	<segmented>0</segmented>
	<object>
		<name>building</name>
		<pose>Unspecified</pose>
		<truncated>0</truncated>
		<difficult>0</difficult>
		<bndbox>
			<xmin>159</xmin>
			<ymin>84</ymin>
			<xmax>357</xmax>
			<ymax>315</ymax>
		</bndbox>
	</object>
	<object>
		<name>building</name>
		<pose>Unspecified</pose>
		<truncated>1</truncated>
		<difficult>0</difficult>
		<bndbox>
			<xmin>1</xmin>
			<ymin>128</ymin>
			<xmax>48</xmax>
			<ymax>233</ymax>
		</bndbox>
	</object>
	<object>
		<name>building</name>
		<pose>Unspecified</pose>
		<truncated>0</truncated>
		<difficult>0</difficult>
		<bndbox>
			<xmin>50</xmin>
			<ymin>147</ymin>
			<xmax>142</xmax>
			<ymax>234</ymax>
		</bndbox>
	</object>
	<object>
		<name>building</name>
		<pose>Unspecified</pose>
		<truncated>0</truncated>
		<difficult>0</difficult>
		<bndbox>
			<xmin>533</xmin>
			<ymin>202</ymin>
			<xmax>594</xmax>
			<ymax>259</ymax>
		</bndbox>
	</object>
	<object>
		<name>tree</name>
		<pose>Unspecified</pose>
		<truncated>0</truncated>
		<difficult>0</difficult>
		<bndbox>
			<xmin>390</xmin>
			<ymin>25</ymin>
			<xmax>531</xmax>
			<ymax>289</ymax>
		</bndbox>
	</object>
	<object>
		<name>tree</name>
		<pose>Unspecified</pose>
		<truncated>0</truncated>
		<difficult>0</difficult>
		<bndbox>
			<xmin>68</xmin>
			<ymin>18</ymin>
			<xmax>232</xmax>
			<ymax>299</ymax>
		</bndbox>
	</object>
	<object>
		<name>grass</name>
		<pose>Unspecified</pose>
		<truncated>1</truncated>
		<difficult>0</difficult>
		<bndbox>
			<xmin>145</xmin>
			<ymin>300</ymin>
			<xmax>600</xmax>
			<ymax>400</ymax>
		</bndbox>
	</object>
	<object>
		<name>sky</name>
		<pose>Unspecified</pose>
		<truncated>1</truncated>
		<difficult>0</difficult>
		<bndbox>
			<xmin>1</xmin>
			<ymin>1</ymin>
			<xmax>600</xmax>
			<ymax>95</ymax>
		</bndbox>
	</object>
</annotation>
