<annotation verified="yes">
	<folder>object_detection</folder>
	<filename>1GpAZWBNs87nnrKnUTxE-I2k3cE57zh7U.jpg</filename>
	<path>/object_detection/1GpAZWBNs87nnrKnUTxE-I2k3cE57zh7U.jpg</path>
	<source>
		<database>Unknown</database>
	</source>
	<size>
		<width>640</width>
		<height>640</height>
		<depth>3</depth>
	</size>
	<segmented>0</segmented>
	<object>
		<name>fireplace</name>
		<pose>Unspecified</pose>
		<truncated>0</truncated>
		<difficult>0</difficult>
		<bndbox>
			<xmin>3</xmin>
			<ymin>176</ymin>
			<xmax>365</xmax>
			<ymax>434</ymax>
		</bndbox>
	</object>
	<object>
		<name>pizza</name>
		<pose>Unspecified</pose>
		<truncated>0</truncated>
		<difficult>0</difficult>
		<bndbox>
			<xmin>292</xmin>
			<ymin>354</ymin>
			<xmax>622</xmax>
			<ymax>487</ymax>
		</bndbox>
	</object>
</annotation>
