<annotation verified="yes">
	<folder>object_detection</folder>
	<filename>1lGhziR0K8odTsKg-LIgvhR4Yag5ThhvG.jpg</filename>
	<path>/object_detection/1lGhziR0K8odTsKg-LIgvhR4Yag5ThhvG.jpg</path>
	<source>
		<database>Unknown</database>
	</source>
	<size>
		<width>640</width>
		<height>581</height>
		<depth>3</depth>
	</size>
	<segmented>0</segmented>
	<object>
		<name>building</name>
		<pose>Unspecified</pose>
		<truncated>0</truncated>
		<difficult>0</difficult>
		<bndbox>
			<xmin>58</xmin>
			<ymin>65</ymin>
			<xmax>574</xmax>
			<ymax>476</ymax>
		</bndbox>
	</object>
	<object>
		<name>bench</name>
		<pose>Unspecified</pose>
		<truncated>0</truncated>
		<difficult>0</difficult>
		<bndbox>
			<xmin>58</xmin>
			<ymin>382</ymin>
			<xmax>172</xmax>
			<ymax>472</ymax>
		</bndbox>
	</object>
</annotation>
