<annotation verified="yes">
	<folder>object_detection</folder>
	<filename>1nrVBpB94W3Q75uY_EGqJzWPpFU5cO-wC.jpg</filename>
	<path>/object_detection/1nrVBpB94W3Q75uY_EGqJzWPpFU5cO-wC.jpg</path>
	<source>
		<database>Unknown</database>
	</source>
	<size>
		<width>640</width>
		<height>426</height>
		<depth>3</depth>
	</size>
	<segmented>0</segmented>
	<object>
		<name>vegetation</name>
		<pose>Unspecified</pose>
		<truncated>1</truncated>
		<difficult>0</difficult>
		<bndbox>
			<xmin>1</xmin>
			<ymin>133</ymin>
			<xmax>374</xmax>
			<ymax>426</ymax>
		</bndbox>
	</object>
	<object>
		<name>tree</name>
		<pose>Unspecified</pose>
		<truncated>1</truncated>
		<difficult>0</difficult>
		<bndbox>
			<xmin>268</xmin>
			<ymin>1</ymin>
			<xmax>358</xmax>
			<ymax>118</ymax>
		</bndbox>
	</object>
	<object>
		<name>tree</name>
		<pose>Unspecified</pose>
		<truncated>1</truncated>
		<difficult>0</difficult>
		<bndbox>
			<xmin>138</xmin>
			<ymin>1</ymin>
			<xmax>218</xmax>
			<ymax>117</ymax>
		</bndbox>
	</object>
	<object>
		<name>tree</name>
		<pose>Unspecified</pose>
		<truncated>1</truncated>
		<difficult>0</difficult>
		<bndbox>
			<xmin>70</xmin>
			<ymin>1</ymin>
			<xmax>144</xmax>
			<ymax>85</ymax>
		</bndbox>
	</object>
</annotation>
