<annotation verified="yes">
	<folder>object_detection</folder>
	<filename>1OU1VNuXbM888OTdzyxRR-rCpQxI_rTrF.jpg</filename>
	<path>/object_detection/1OU1VNuXbM888OTdzyxRR-rCpQxI_rTrF.jpg</path>
	<source>
		<database>Unknown</database>
	</source>
	<size>
		<width>640</width>
		<height>800</height>
		<depth>3</depth>
	</size>
	<segmented>0</segmented>
	<object>
		<name>boat</name>
		<pose>Unspecified</pose>
		<truncated>0</truncated>
		<difficult>0</difficult>
		<bndbox>
			<xmin>427</xmin>
			<ymin>502</ymin>
			<xmax>577</xmax>
			<ymax>661</ymax>
		</bndbox>
	</object>
	<object>
		<name>boat</name>
		<pose>Unspecified</pose>
		<truncated>1</truncated>
		<difficult>0</difficult>
		<bndbox>
			<xmin>1</xmin>
			<ymin>497</ymin>
			<xmax>183</xmax>
			<ymax>565</ymax>
		</bndbox>
	</object>
	<object>
		<name>boat</name>
		<pose>Unspecified</pose>
		<truncated>0</truncated>
		<difficult>0</difficult>
		<bndbox>
			<xmin>179</xmin>
			<ymin>484</ymin>
			<xmax>294</xmax>
			<ymax>530</ymax>
		</bndbox>
	</object>
	<object>
		<name>boat</name>
		<pose>Unspecified</pose>
		<truncated>0</truncated>
		<difficult>0</difficult>
		<bndbox>
			<xmin>288</xmin>
			<ymin>473</ymin>
			<xmax>343</xmax>
			<ymax>507</ymax>
		</bndbox>
	</object>
	<object>
		<name>river</name>
		<pose>Unspecified</pose>
		<truncated>1</truncated>
		<difficult>0</difficult>
		<bndbox>
			<xmin>1</xmin>
			<ymin>464</ymin>
			<xmax>640</xmax>
			<ymax>794</ymax>
		</bndbox>
	</object>
	<object>
		<name>power pole</name>
		<pose>Unspecified</pose>
		<truncated>1</truncated>
		<difficult>0</difficult>
		<bndbox>
			<xmin>1</xmin>
			<ymin>1</ymin>
			<xmax>195</xmax>
			<ymax>465</ymax>
		</bndbox>
	</object>
	<object>
		<name>sky</name>
		<pose>Unspecified</pose>
		<truncated>1</truncated>
		<difficult>0</difficult>
		<bndbox>
			<xmin>123</xmin>
			<ymin>1</ymin>
			<xmax>640</xmax>
			<ymax>385</ymax>
		</bndbox>
	</object>
	<object>
		<name>vegetation</name>
		<pose>Unspecified</pose>
		<truncated>0</truncated>
		<difficult>0</difficult>
		<bndbox>
			<xmin>156</xmin>
			<ymin>382</ymin>
			<xmax>482</xmax>
			<ymax>468</ymax>
		</bndbox>
	</object>
	<object>
		<name>vegetation</name>
		<pose>Unspecified</pose>
		<truncated>1</truncated>
		<difficult>0</difficult>
		<bndbox>
			<xmin>511</xmin>
			<ymin>272</ymin>
			<xmax>640</xmax>
			<ymax>475</ymax>
		</bndbox>
	</object>
</annotation>
