<annotation verified="yes">
	<folder>object_detection</folder>
	<filename>1rwGrf-wFY657XoJAPMk-sKZ_H12j3npC.jpg</filename>
	<path>/object_detection/1rwGrf-wFY657XoJAPMk-sKZ_H12j3npC.jpg</path>
	<source>
		<database>Unknown</database>
	</source>
	<size>
		<width>640</width>
		<height>640</height>
		<depth>3</depth>
	</size>
	<segmented>0</segmented>
	<object>
		<name>building</name>
		<pose>Unspecified</pose>
		<truncated>1</truncated>
		<difficult>0</difficult>
		<bndbox>
			<xmin>2</xmin>
			<ymin>1</ymin>
			<xmax>639</xmax>
			<ymax>632</ymax>
		</bndbox>
	</object>
	<object>
		<name>sign</name>
		<pose>Unspecified</pose>
		<truncated>0</truncated>
		<difficult>0</difficult>
		<bndbox>
			<xmin>244</xmin>
			<ymin>209</ymin>
			<xmax>446</xmax>
			<ymax>253</ymax>
		</bndbox>
	</object>
</annotation>
