<annotation verified="yes">
	<folder>object_detection</folder>
	<filename>1XnWdAZCHqZyPoevGcgC5qyy42t-mXdvB.jpg</filename>
	<path>/object_detection/1XnWdAZCHqZyPoevGcgC5qyy42t-mXdvB.jpg</path>
	<source>
		<database>Unknown</database>
	</source>
	<size>
		<width>500</width>
		<height>375</height>
		<depth>3</depth>
	</size>
	<segmented>0</segmented>
	<object>
		<name>building</name>
		<pose>Unspecified</pose>
		<truncated>1</truncated>
		<difficult>0</difficult>
		<bndbox>
			<xmin>1</xmin>
			<ymin>6</ymin>
			<xmax>500</xmax>
			<ymax>304</ymax>
		</bndbox>
	</object>
	<object>
		<name>tree</name>
		<pose>Unspecified</pose>
		<truncated>0</truncated>
		<difficult>0</difficult>
		<bndbox>
			<xmin>262</xmin>
			<ymin>40</ymin>
			<xmax>415</xmax>
			<ymax>108</ymax>
		</bndbox>
	</object>
	<object>
		<name>tree</name>
		<pose>Unspecified</pose>
		<truncated>1</truncated>
		<difficult>0</difficult>
		<bndbox>
			<xmin>418</xmin>
			<ymin>20</ymin>
			<xmax>500</xmax>
			<ymax>99</ymax>
		</bndbox>
	</object>
	<object>
		<name>vegetation</name>
		<pose>Unspecified</pose>
		<truncated>1</truncated>
		<difficult>0</difficult>
		<bndbox>
			<xmin>1</xmin>
			<ymin>237</ymin>
			<xmax>145</xmax>
			<ymax>375</ymax>
		</bndbox>
	</object>
</annotation>
