<annotation verified="yes">
	<folder>object_detection</folder>
	<filename>1Xt4DXdZ_Jyu1GFSSz0dDyWY5jIs4nFr5.jpg</filename>
	<path>/object_detection/1Xt4DXdZ_Jyu1GFSSz0dDyWY5jIs4nFr5.jpg</path>
	<source>
		<database>Unknown</database>
	</source>
	<size>
		<width>500</width>
		<height>335</height>
		<depth>3</depth>
	</size>
	<segmented>0</segmented>
	<object>
		<name>sea</name>
		<pose>Unspecified</pose>
		<truncated>1</truncated>
		<difficult>0</difficult>
		<bndbox>
			<xmin>1</xmin>
			<ymin>140</ymin>
			<xmax>253</xmax>
			<ymax>206</ymax>
		</bndbox>
	</object>
	<object>
		<name>street</name>
		<pose>Unspecified</pose>
		<truncated>1</truncated>
		<difficult>0</difficult>
		<bndbox>
			<xmin>1</xmin>
			<ymin>207</ymin>
			<xmax>500</xmax>
			<ymax>335</ymax>
		</bndbox>
	</object>
</annotation>
